systemtools/__init__.py
systemtools/basics.py
systemtools/config.py
systemtools/duration.py
systemtools/enumeration.py
systemtools/file.py
systemtools/jupyterutils.py
systemtools/location.py
systemtools/logger.py
systemtools/number.py
systemtools/printer.py
systemtools/pythonpath.py
systemtools/synchronized.py
systemtools/system.py
systemtools/test/__init__.py
systemtools/test/basics.py
systemtools/test/clearterminaltest.py
systemtools/test/duration.py
systemtools/test/extract-gz-test.py
systemtools/test/filetest.py
systemtools/test/killbill-test.py
systemtools/test/location.py
systemtools/test/number.py
systemtools/test/printertest.py
systemtools/test/queuetest.py
systemtools/test/setpythonpath.py
systemtools/test/sys-test.py
systemtools/test/systemtest.py
systools-0.1.3.dist-info/LICENCE.txt
systools-0.1.3.dist-info/METADATA
systools-0.1.3.dist-info/WHEEL
systools-0.1.3.dist-info/top_level.txt
systools-0.1.3.dist-info/RECORD
