Metadata-Version: 2.1
Name: systools
Version: 0.1.3
Summary: A project gathering basic Python tools.
Home-page: https://github.com/hayj/SystemTools
Author: hayj
License-File: LICENCE.txt
Requires-Dist: psutil
Requires-Dist: parsedatetime
Requires-Dist: arrow
Requires-Dist: pytz
Requires-Dist: tzlocal
Requires-Dist: sh
Requires-Dist: tabulate
Requires-Dist: requests
Requires-Dist: xtract
Requires-Dist: unidecode
Requires-Dist: pathlib ; python_version < "3.4"
